__init__.py
data/__init__.py
data/br/fakebonds.csv
data/br/ipca.csv
data/data.py
interesting-0.0.2.dist-info/METADATA
interesting-0.0.2.dist-info/WHEEL
interesting-0.0.2.dist-info/licenses/LICENSE
interesting/__init__.py
interesting/bonds.py
interesting/cashflow.py
interesting/inflation.py
interesting/interest.py
interesting/portfolio.py
interesting/time.py
interesting/utils.py
interesting/value.py
interesting-0.0.2.dist-info/RECORD
