Metadata-Version: 2.1
Name: interesting
Version: 0.0.2
Summary: A corporate finance package focused on Brazilian Fixed Income titles.
Author-Email: Daniel Ruiz <daniel.rocharuiz@bocconialumni.it>
License: MIT
Requires-Python: >=3.12
Requires-Dist: coverage
Requires-Dist: ipywidgets
Requires-Dist: matplotlib
Requires-Dist: numpy-financial
Requires-Dist: pandas
Requires-Dist: pandas-stubs
Requires-Dist: pdm
Requires-Dist: pre-commit
Requires-Dist: pyarrow
Requires-Dist: pydantic
Requires-Dist: pytest
Requires-Dist: ruff
Requires-Dist: setuptools
Requires-Dist: tqdm
Requires-Dist: types-python-dateutil
